odoo/addons/sale_coupon_most_expensive/README.rst
odoo/addons/sale_coupon_most_expensive/__init__.py
odoo/addons/sale_coupon_most_expensive/__manifest__.py
odoo/addons/sale_coupon_most_expensive/i18n/fr.po
odoo/addons/sale_coupon_most_expensive/i18n/sale_coupon_most_expensive.pot
odoo/addons/sale_coupon_most_expensive/models/__init__.py
odoo/addons/sale_coupon_most_expensive/models/sale_coupon_reward.py
odoo/addons/sale_coupon_most_expensive/models/sale_order.py
odoo/addons/sale_coupon_most_expensive/readme/CONTRIBUTORS.rst
odoo/addons/sale_coupon_most_expensive/readme/DESCRIPTION.rst
odoo/addons/sale_coupon_most_expensive/static/description/icon.png
odoo/addons/sale_coupon_most_expensive/static/description/index.html
odoo/addons/sale_coupon_most_expensive/tests/__init__.py
odoo/addons/sale_coupon_most_expensive/tests/test_discount_apply_on.py
odoo13_addon_sale_coupon_most_expensive-13.0.1.0.1.dist-info/METADATA
odoo13_addon_sale_coupon_most_expensive-13.0.1.0.1.dist-info/WHEEL
odoo13_addon_sale_coupon_most_expensive-13.0.1.0.1.dist-info/top_level.txt
odoo13_addon_sale_coupon_most_expensive-13.0.1.0.1.dist-info/RECORD
